MANIFEST.in
README.md
requirements.txt
setup.py
./src/scripts/clusto-dhcpd
./src/scripts/clusto-httpd
./src/scripts/clusto-update-db
./src/scripts/clusto-update-info
src/clusto/__init__.py
src/clusto/exceptions.py
src/clusto/schema.py
src/clusto/script_helper.py
src/clusto/util.py
src/clusto.egg-info/PKG-INFO
src/clusto.egg-info/SOURCES.txt
src/clusto.egg-info/dependency_links.txt
src/clusto.egg-info/entry_points.txt
src/clusto.egg-info/not-zip-safe
src/clusto.egg-info/pbr.json
src/clusto.egg-info/requires.txt
src/clusto.egg-info/top_level.txt
src/clusto/commands/__init__.py
src/clusto/commands/allocate.py
src/clusto/commands/attr.py
src/clusto/commands/console.py
src/clusto/commands/deallocate.py
src/clusto/commands/info.py
src/clusto/commands/initdb.py
src/clusto/commands/list_all.py
src/clusto/commands/list_pool.py
src/clusto/commands/pool.py
src/clusto/commands/reboot.py
src/clusto/commands/rename.py
src/clusto/commands/shell.py
src/clusto/commands/tree.py
src/clusto/drivers/__init__.py
src/clusto/drivers/base/__init__.py
src/clusto/drivers/base/clustodriver.py
src/clusto/drivers/base/clustometa.py
src/clusto/drivers/base/controller.py
src/clusto/drivers/base/device.py
src/clusto/drivers/base/driver.py
src/clusto/drivers/base/location.py
src/clusto/drivers/base/resourcemanager.py
src/clusto/drivers/categories/__init__.py
src/clusto/drivers/categories/pool.py
src/clusto/drivers/devices/__init__.py
src/clusto/drivers/devices/appliance/__init__.py
src/clusto/drivers/devices/appliance/basicappliance.py
src/clusto/drivers/devices/common/__init__.py
src/clusto/drivers/devices/common/ipmixin.py
src/clusto/drivers/devices/common/portmixin.py
src/clusto/drivers/devices/consoleservers/__init__.py
src/clusto/drivers/devices/consoleservers/basicconsoleserver.py
src/clusto/drivers/devices/networkswitches/__init__.py
src/clusto/drivers/devices/networkswitches/basicnetworkswitch.py
src/clusto/drivers/devices/powerstrips/__init__.py
src/clusto/drivers/devices/powerstrips/basicpowerstrip.py
src/clusto/drivers/devices/servers/__init__.py
src/clusto/drivers/devices/servers/basicserver.py
src/clusto/drivers/locations/__init__.py
src/clusto/drivers/locations/datacenters/__init__.py
src/clusto/drivers/locations/datacenters/basiccage.py
