Metadata-Version: 1.0
Name: clusto
Version: 0.7.8
Summary: Cluster management and inventory system
Home-page: UNKNOWN
Author: Ron Gorodetzky
Author-email: ron@parktree.net
License: BSD
Platform: UNKNOWN
